{
    "format_version": "1.20.0",
    "minecraft:block": {
        "description": {
            "identifier": "hy:deepslate_suspicious_lapis_ore",
            "menu_category": {
                "category": "nature",
                "group": "itemGroup.name.ore"
            }
        },
        "components": {
            "minecraft:display_name": "hy.block.deepslate_suspicious_lapis_ore",
            "minecraft:loot": "loot_tables/empty.json",
            "minecraft:destructible_by_mining": {
                "seconds_to_destroy": 0.8
            },
            "minecraft:destructible_by_explosion": {
                "explosion_resistance": 3.0
            },
            "minecraft:map_color": "#565656",
            "minecraft:on_player_destroyed": {
                "event": "hy.spawn_loot",
                "condition": "query.equipped_item_any_tag('slot.weapon.mainhand', 'minecraft:is_pickaxe')"
            },
            "tag:minecraft:stone_pick_diggable": {}
        },
        "events": {
            "hy.spawn_loot": {
                "randomize": [
                    {
                        "weight": 8,
                        "spawn_loot": {
                            "table": "loot_tables/blocks/suspicious_ores/coal.json"
                        }
                    },
                    {
                        "weight": 5,
                        "run_command": {
                            "target": "self",
                            "command": [
                                "function gameplay/blocks/sus_ores/1"
                            ]
                        }
                    },
                    {
                        "weight": 1,
                        "run_command": {
                            "target": "self",
                            "command": [
                                "function gameplay/blocks/sus_ores/2"
                            ]
                        }
                    }
                ]
            }
        }
    }
}